endpoints/__init__.py
endpoints/chat.py
endpoints/completions.py
endpoints/models.py
tests/__init__.py
tests/test_chat.py
tests/test_client.py
tests/test_completions.py
txtgenai-0.1.0.dist-info/LICENSE
txtgenai-0.1.0.dist-info/METADATA
txtgenai-0.1.0.dist-info/WHEEL
txtgenai-0.1.0.dist-info/top_level.txt
txtgenai-0.1.0.dist-info/RECORD
