Metadata-Version: 2.1
Name: txtgenai
Version: 0.1.0
Summary: A Python package for advanced text generation
Home-page: https://github.com/Sohail-Shaikh-07/txtgenai.git
Author: Sohail Shaikh
Author-email: sohailshaikharifshaikh07@gmail.com
Classifier: Programming Language :: Python :: 3
Classifier: License :: OSI Approved :: MIT License
Classifier: Operating System :: OS Independent
Requires-Python: >=3.6
License-File: LICENSE
Requires-Dist: requests>=2.25.1
